get_jakdojade/__init__.py
get_jakdojade-0.0.2.dist-info/LICENSE
get_jakdojade-0.0.2.dist-info/METADATA
get_jakdojade-0.0.2.dist-info/WHEEL
get_jakdojade-0.0.2.dist-info/top_level.txt
get_jakdojade-0.0.2.dist-info/RECORD
