Metadata-Version: 2.1
Name: get-jakdojade
Version: 0.0.2
Summary: Jakdojade URL generator
Home-page: https://github.com/Behoston/get_jakdojade
Author: Behoston
Author-email: mlegiecki@gmail.com
License: MIT
Platform: any
Classifier: Development Status :: 3 - Alpha
Classifier: Environment :: Other Environment
Classifier: Intended Audience :: Developers
Classifier: License :: OSI Approved :: MIT License
Classifier: Natural Language :: English
Classifier: Operating System :: OS Independent
Classifier: Programming Language :: Python
Classifier: Programming Language :: Python :: 3
Classifier: Programming Language :: Python :: 3.7
Classifier: Programming Language :: Python :: 3.8
Classifier: Programming Language :: Python :: 3.9
Classifier: Programming Language :: Python :: 3.10
Classifier: Topic :: Software Development :: Libraries :: Python Modules
Classifier: Topic :: Software Development
Classifier: Typing :: Typed
Requires-Python: >=3.6
License-File: LICENSE
